Workbook

Sheet Dashboard
A1: Dropshipping Business Tracker
A3: Total Orders | B3: Total Revenue $ | C3: Net Profit $ | D3: Avg Margin %
A4: =COUNTA(Orders!A:A)-1 | B4: =SUM(Orders!F:F) | C4: =SUM(Orders!I:I) | D4: =AVERAGE(Orders!J:J)

Sheet Products
A1: Product Name | B1: Supplier | C1: Supplier Cost $ | D1: Selling Price $ | E1: Margin $ | F1: Margin % | G1: Status
A2: Wireless Phone Charger | B2: AliExpress - Tech Store | C2: 8.50 | D2: 24.99 | E2: =D2-C2 | F2: =TEXT((D2-C2)/D2,"0%")
A3: Wireless Phone Charger | B3: AliExpress - Tech Store | C3: 8.50 | D3: 24.99 | E3: =D3-C3 | F3: =TEXT((D3-C3)/D3,"0%")
A4: Wireless Phone Charger | B4: AliExpress - Tech Store | C4: 8.50 | D4: 24.99 | E4: =D4-C4 | F4: =TEXT((D4-C4)/D4,"0%")
A5: Wireless Phone Charger | B5: AliExpress - Tech Store | C5: 8.50 | D5: 24.99 | E5: =D5-C5 | F5: =TEXT((D5-C5)/D5,"0%")
A6: Wireless Phone Charger | B6: AliExpress - Tech Store | C6: 8.50 | D6: 24.99 | E6: =D6-C6 | F6: =TEXT((D6-C6)/D6,"0%")
A7: Wireless Phone Charger | B7: AliExpress - Tech Store | C7: 8.50 | D7: 24.99 | E7: =D7-C7 | F7: =TEXT((D7-C7)/D7,"0%")
A8: Wireless Phone Charger | B8: AliExpress - Tech Store | C8: 8.50 | D8: 24.99 | E8: =D8-C8 | F8: =TEXT((D8-C8)/D8,"0%")
A9: Wireless Phone Charger | B9: AliExpress - Tech Store | C9: 8.50 | D9: 24.99 | E9: =D9-C9 | F9: =TEXT((D9-C9)/D9,"0%")
A10: Wireless Phone Charger | B10: AliExpress - Tech Store | C10: 8.50 | D10: 24.99 | E10: =D10-C10 | F10: =TEXT((D10-C10)/D10,"0%")
A11: Wireless Phone Charger | B11: AliExpress - Tech Store | C11: 8.50 | D11: 24.99 | E11: =D11-C11 | F11: =TEXT((D11-C11)/D11,"0%")
A12: Wireless Phone Charger | B12: AliExpress - Tech Store | C12: 8.50 | D12: 24.99 | E12: =D12-C12 | F12: =TEXT((D12-C12)/D12,"0%")
A13: Wireless Phone Charger | B13: AliExpress - Tech Store | C13: 8.50 | D13: 24.99 | E13: =D13-C13 | F13: =TEXT((D13-C13)/D13,"0%")
... A21: Wireless Phone Charger | B21: AliExpress - Tech Store | C21: 8.50 | D21: 24.99 | E21: =D21-C21 | F21: =TEXT((D21-C21)/D21,"0%")

Sheet Orders
A1: Order Date | B1: Order ID | C1: Product | D1: Qty | E1: Platform | F1: Revenue $ | G1: Supplier Cost $ | H1: Ads Cost $ | I1: Platform Fee $ | J1: Net Profit $
A2: 2024-01-15 | B2: ORD-5829 | C2: Wireless Phone Charger | D2: 2 | F2: 49.98 | G2: 17 | H2: 8 | I2: 2.50 | J2: =F2-G2-H2-I2
A3: 2024-01-15 | B3: ORD-5829 | C3: Wireless Phone Charger | D3: 2 | F3: 49.98 | G3: 17 | H3: 8 | I3: 2.50 | J3: =F3-G3-H3-I3
A4: 2024-01-15 | B4: ORD-5829 | C4: Wireless Phone Charger | D4: 2 | F4: 49.98 | G4: 17 | H4: 8 | I4: 2.50 | J4: =F4-G4-H4-I4
A5: 2024-01-15 | B5: ORD-5829 | C5: Wireless Phone Charger | D5: 2 | F5: 49.98 | G5: 17 | H5: 8 | I5: 2.50 | J5: =F5-G5-H5-I5
A6: 2024-01-15 | B6: ORD-5829 | C6: Wireless Phone Charger | D6: 2 | F6: 49.98 | G6: 17 | H6: 8 | I6: 2.50 | J6: =F6-G6-H6-I6
A7: 2024-01-15 | B7: ORD-5829 | C7: Wireless Phone Charger | D7: 2 | F7: 49.98 | G7: 17 | H7: 8 | I7: 2.50 | J7: =F7-G7-H7-I7
A8: 2024-01-15 | B8: ORD-5829 | C8: Wireless Phone Charger | D8: 2 | F8: 49.98 | G8: 17 | H8: 8 | I8: 2.50 | J8: =F8-G8-H8-I8
A9: 2024-01-15 | B9: ORD-5829 | C9: Wireless Phone Charger | D9: 2 | F9: 49.98 | G9: 17 | H9: 8 | I9: 2.50 | J9: =F9-G9-H9-I9
A10: 2024-01-15 | B10: ORD-5829 | C10: Wireless Phone Charger | D10: 2 | F10: 49.98 | G10: 17 | H10: 8 | I10: 2.50 | J10: =F10-G10-H10-I10
A11: 2024-01-15 | B11: ORD-5829 | C11: Wireless Phone Charger | D11: 2 | F11: 49.98 | G11: 17 | H11: 8 | I11: 2.50 | J11: =F11-G11-H11-I11
A12: 2024-01-15 | B12: ORD-5829 | C12: Wireless Phone Charger | D12: 2 | F12: 49.98 | G12: 17 | H12: 8 | I12: 2.50 | J12: =F12-G12-H12-I12
A13: 2024-01-15 | B13: ORD-5829 | C13: Wireless Phone Charger | D13: 2 | F13: 49.98 | G13: 17 | H13: 8 | I13: 2.50 | J13: =F13-G13-H13-I13
... A26: 2024-01-15 | B26: ORD-5829 | C26: Wireless Phone Charger | D26: 2 | F26: 49.98 | G26: 17 | H26: 8 | I26: 2.50 | J26: =F26-G26-H26-I26

Sheet Suppliers
A1: Supplier | B1: Platform | C1: Lead Time (days) | D1: Products | E1: Rating
A2: AliExpress - Tech Seller | C2: 14 | D2: Electronics, Phone accessories
A3: AliExpress - Tech Seller | C3: 14 | D3: Electronics, Phone accessories
A4: AliExpress - Tech Seller | C4: 14 | D4: Electronics, Phone accessories
A5: AliExpress - Tech Seller | C5: 14 | D5: Electronics, Phone accessories
A6: AliExpress - Tech Seller | C6: 14 | D6: Electronics, Phone accessories
A7: AliExpress - Tech Seller | C7: 14 | D7: Electronics, Phone accessories
A8: AliExpress - Tech Seller | C8: 14 | D8: Electronics, Phone accessories
A9: AliExpress - Tech Seller | C9: 14 | D9: Electronics, Phone accessories

Sheet Monthly P&L
A1: Reports — Auto-Generated
A3: Business Summary
A4: Total Orders | B4: =COUNTA(Orders!A:A)-1
A5: Gross Revenue | B5: =SUM(Orders!F:F)
A6: Net Profit | B6: =SUM(Orders!J:J)
