Workbook

Sheet START HERE
B2: 🛍️ ETSY SHOP ANALYTICS TRACKER
B4: Etsy Sales, Revenue & Product Performance Google Sheets
B6: STEP 1 — Fill in “Sales”
B7: Every sale: product, buyer country, revenue, and date.
B9: STEP 2 — Fill in “Products”
B10: All products with sales count, revenue, and performance.
B12: STEP 3 — Fill in “Monthly Revenue”
B13: Month-by-month revenue and sales count.
B15: Then open the Dashboard — everything calculates automatically.
B17: TIP: Delete the sample rows once you've seen how it works.
B19: TIP: On Google Sheets? File → Make a copy first, then edit your copy.
B21: TIP: Columns with dropdowns keep your data clean — use them.
B23: Need help? Message NasriTools on Etsy — I reply fast. 🧡

Sheet Sales
A1: Date | B1: Order ID | C1: Product | D1: Qty | E1: Revenue $ | F1: Etsy Fee $ | G1: Net $ | H1: Country
A2: 46174 | B2: 3856291047 | C2: Budget Tracker Template | D2: 1 | E2: 12 | F2: 1.8 | G2: =E2-F2 | H2: United States
A3: 46180 | B3: 2699403733 | C3: Budget Tracker Template | D3: 0.7 | E3: 8.4 | F3: 1.26 | G3: =E3-F3 | H3: United States
A4: 46186 | B4: 5013178361 | D4: 1.3 | E4: 15.6 | F4: 2.34 | G4: =E4-F4
A5: 46189 | B5: 3277847390 | C5: Budget Tracker Template | D5: 0.85 | E5: 10.2 | F5: 1.53 | G5: =E5-F5 | H5: United States
A6: 46195 | B6: 4434734704 | C6: Budget Tracker Template | D6: 1.15 | E6: 13.8 | F6: 2.07 | G6: =E6-F6 | H6: United States
A7: 46201 | B7: 2313774628 | D7: 0.6 | E7: 7.2 | F7: 1.08 | G7: =E7-F7
A8: 46176 | B8: 5591622018 | C8: Budget Tracker Template | D8: 1.45 | E8: 17.4 | F8: 2.61 | G8: =E8-F8 | H8: United States
A9: 46182 | B9: 3663476495 | C9: Budget Tracker Template | D9: 0.95 | E9: 11.4 | F9: 1.71 | G9: =E9-F9 | H9: United States
A10: 46188 | B10: 4820363809 | D10: 1.25 | E10: 15 | F10: 2.25 | G10: =E10-F10
A11: 46191 | B11: 3085032838 | C11: Budget Tracker Template | D11: 0.8 | E11: 9.6 | F11: 1.44 | G11: =E11-F11 | H11: United States
A12: 46197 | B12: 4241920152 | C12: Budget Tracker Template | D12: 1.1 | E12: 13.2 | F12: 1.98 | G12: =E12-F12 | H12: United States
A13: 46175 | B13: 2892218285 | D13: 0.75 | E13: 9 | F13: 1.35 | G13: =E13-F13

Sheet Dashboard
B2: 📊 ETSY SHOP ANALYTICS TRACKER — DASHBOARD
B4: TOTAL SALES | D4: TOTAL REVENUE | F4: AVG ORDER VALUE | H4: TOTAL PRODUCTS
B5: =COUNTA(Sales!A:A)-1 | D5: =SUM(Sales!E:E) | F5: =AVERAGE(Sales!E:E) | H5: =COUNTA(Products!A:A)-1
B8: WHAT'S INSIDE
B9: 🧾 Sales — Every sale: product, buyer country, revenue, and date.
B10: 📦 Products — All products with sales count, revenue, and performance.
B11: 📅 Monthly Revenue — Month-by-month revenue and sales count.
B12: 📊 Annual Report — Annual Etsy shop performance summary.
B14: Numbers update automatically as you fill the other tabs. Start with sample data deleted.

Sheet Products
A1: Product | B1: Price $ | C1: Total Sales | D1: Revenue $ | E1: Views | F1: Conversion % | G1: Status
A2: Budget Tracker Template | B2: 12 | C2: 45 | D2: 540 | E2: 1200 | F2: =TEXT(C2/E2,"0.0%") | G2: Active
A3: Budget Tracker Template | B3: 8.4 | C3: 31.5 | D3: 378 | E3: 840 | F3: =TEXT(C3/E3,"0.0%") | G3: Inactive
B4: 15.6 | C4: 58.5 | D4: 702 | E4: 1560 | F4: =TEXT(C4/E4,"0.0%") | G4: Draft
A5: Budget Tracker Template | B5: 10.2 | C5: 38.25 | D5: 459 | E5: 1020 | F5: =TEXT(C5/E5,"0.0%") | G5: Sold Out
A6: Budget Tracker Template | B6: 13.8 | C6: 51.75 | D6: 621 | E6: 1380 | F6: =TEXT(C6/E6,"0.0%") | G6: Active
B7: 7.2 | C7: 27 | D7: 324 | E7: 720 | F7: =TEXT(C7/E7,"0.0%") | G7: Inactive
A8: Budget Tracker Template | B8: 17.4 | C8: 65.25 | D8: 783 | E8: 1740 | F8: =TEXT(C8/E8,"0.0%") | G8: Draft
A9: Budget Tracker Template | B9: 11.4 | C9: 42.75 | D9: 513 | E9: 1140 | F9: =TEXT(C9/E9,"0.0%") | G9: Sold Out
B10: 15 | C10: 56.25 | D10: 675 | E10: 1500 | F10: =TEXT(C10/E10,"0.0%") | G10: Active
A11: Budget Tracker Template | B11: 9.6 | C11: 36 | D11: 432 | E11: 960 | F11: =TEXT(C11/E11,"0.0%") | G11: Inactive
A12: Budget Tracker Template | B12: 13.2 | C12: 49.5 | D12: 594 | E12: 1320 | F12: =TEXT(C12/E12,"0.0%") | G12: Draft
B13: 9 | C13: 33.75 | D13: 405 | E13: 900 | F13: =TEXT(C13/E13,"0.0%") | G13: Sold Out

Sheet Monthly Revenue
A1: Month | B1: Sales | C1: Revenue $ | D1: Etsy Fees $ | E1: Net $ | F1: Top Product
A2: January 2024 | B2: 34 | C2: 408 | D2: 61 | E2: =C2-D2 | F2: Budget Tracker Template
A3: January 2025 | B3: 23.8 | C3: 286 | D3: 42.7 | E3: =C3-D3 | F3: Budget Tracker Template
A4: January 2026 | B4: 44.2 | C4: 530 | D4: 79.3 | E4: =C4-D4
A5: January 2027 | B5: 28.9 | C5: 347 | D5: 51.85 | E5: =C5-D5 | F5: Budget Tracker Template
A6: January 2028 | B6: 39.1 | C6: 469 | D6: 70.15 | E6: =C6-D6 | F6: Budget Tracker Template
A7: January 2029 | B7: 20.4 | C7: 245 | D7: 36.6 | E7: =C7-D7
A8: January 2030 | B8: 49.3 | C8: 592 | D8: 88.45 | E8: =C8-D8 | F8: Budget Tracker Template
A9: January 2031 | B9: 32.3 | C9: 388 | D9: 57.95 | E9: =C9-D9 | F9: Budget Tracker Template
A10: January 2032 | B10: 42.5 | C10: 510 | D10: 76.25 | E10: =C10-D10
A11: January 2033 | B11: 27.2 | C11: 326 | D11: 48.8 | E11: =C11-D11 | F11: Budget Tracker Template
A12: January 2034 | B12: 37.4 | C12: 449 | D12: 67.1 | E12: =C12-D12 | F12: Budget Tracker Template
A13: January 2035 | B13: 25.5 | C13: 306 | D13: 45.75 | E13: =C13-D13

Sheet Annual Report
B2: 📈 ANNUAL REPORT
B4: Shop Summary
B5: Total Sales | C5: =COUNTA(Sales!A:A)-1
B6: Gross Revenue | C6: =SUM(Sales!E:E)
B7: Net Revenue | C7: =SUM(Sales!G:G)
