Workbook

Sheet 📖 START HERE
A1: Monthly Budget Tracker — Quick Start Guide
B3: Welcome! Follow these 4 steps and your dashboard will fill itself. ✨
A5: 1 | B5: Open the '💵 Transactions' tab and enter your income and expenses in the YELLOW cells.
A7: 2 | B7: Pick a Category and Type (Income/Expense) from the dropdown menus.
A9: 3 | B9: Go to '🏠 DASHBOARD' — your totals, savings rate and charts update automatically.
A11: 4 | B11: Check '📊 Category Summary' to see exactly where your money goes.
B14: 💡 TIPS
B15: • Yellow cells = your input. Everything else is automatic — don't edit formulas.
B16: • You can add or rename categories in the '📊 Category Summary' tab.
B17: • Works in Google Sheets (File → Import → Upload) and Microsoft Excel.
B18: • Change the currency: select cells → Format → Number → Currency.
B21: Need help? Message me on Etsy — I reply within 24h. 🧡 | NasriTools

Sheet 🏠 DASHBOARD
A1: 💰 MONTHLY BUDGET DASHBOARD
A3: TOTAL INCOME | B3: TOTAL EXPENSES | C3: NET SAVINGS | D3: SAVINGS RATE
A4: =SUMIF('💵 Transactions'!$D$3:$D$300,"Income",'💵 Transactions'!$E$3:$E$300) | B4: =SUMIF('💵 Transactions'!$D$3:$D$300,"Expense",'💵 Transactions'!$E$3:$E$300) | C4: =A4-B4 | D4: =IFERROR(C4/A4,0)
A7: TRANSACTIONS | B7: AVG EXPENSE | C7: BIGGEST CATEGORY | D7: TOP SPEND
A8: =COUNTA('💵 Transactions'!$B$3:$B$300) | B8: =IFERROR(B4/COUNTIFS('💵 Transactions'!$D$3:$D$300,"Expense"),0) | C8: =IFERROR(INDEX('📊 Category Summary'!A3:A14,MATCH(MAX('📊 Category Summary'!B3:B14),'📊 Category Summary'!B3:B14,0)),"-") | D8: =IFERROR(MAX('📊 Category Summary'!B3:B14),0)
A30: ✏️ Enter your data in the '💵 Transactions' tab — everything here updates automatically.

Sheet 💵 Transactions
A1: Transactions — Enter your income & expenses here
A2: Date | B2: Description | C2: Category | D2: Type | E2: Amount | F2: Month
A3: 2026-01-05 | B3: Monthly salary | C3: Salary | D3: Income | E3: 2500 | F3: =IF(A3="","",TEXT(A3,"mmm"))
A4: 2026-01-06 | B4: Rent | C4: Housing | D4: Expense | E4: 800 | F4: =IF(A4="","",TEXT(A4,"mmm"))
A5: 2026-01-08 | B5: Groceries | C5: Food | D5: Expense | E5: 120 | F5: =IF(A5="","",TEXT(A5,"mmm"))
F6: =IF(A6="","",TEXT(A6,"mmm"))
F7: =IF(A7="","",TEXT(A7,"mmm"))
F8: =IF(A8="","",TEXT(A8,"mmm"))
F9: =IF(A9="","",TEXT(A9,"mmm"))
F10: =IF(A10="","",TEXT(A10,"mmm"))
F11: =IF(A11="","",TEXT(A11,"mmm"))
F12: =IF(A12="","",TEXT(A12,"mmm"))
F13: =IF(A13="","",TEXT(A13,"mmm"))
F14: =IF(A14="","",TEXT(A14,"mmm"))
F15: =IF(A15="","",TEXT(A15,"mmm"))
F16: =IF(A16="","",TEXT(A16,"mmm"))
F17: =IF(A17="","",TEXT(A17,"mmm"))
... F299: =IF(A299="","",TEXT(A299,"mmm"))

Sheet 📊 Category Summary
A1: Spending by Category
A2: Category | B2: Total Spent | C2: % of Total
A3: Housing | B3: =SUMIFS('💵 Transactions'!$E$3:$E$300,'💵 Transactions'!$C$3:$C$300,$A3,'💵 Transactions'!$D$3:$D$300,"Expense") | C3: =IFERROR(B3/SUM($B$3:$B$14),0)
A4: Food | B4: =SUMIFS('💵 Transactions'!$E$3:$E$300,'💵 Transactions'!$C$3:$C$300,$A4,'💵 Transactions'!$D$3:$D$300,"Expense") | C4: =IFERROR(B4/SUM($B$3:$B$14),0)
A5: Transport | B5: =SUMIFS('💵 Transactions'!$E$3:$E$300,'💵 Transactions'!$C$3:$C$300,$A5,'💵 Transactions'!$D$3:$D$300,"Expense") | C5: =IFERROR(B5/SUM($B$3:$B$14),0)
A6: Utilities | B6: =SUMIFS('💵 Transactions'!$E$3:$E$300,'💵 Transactions'!$C$3:$C$300,$A6,'💵 Transactions'!$D$3:$D$300,"Expense") | C6: =IFERROR(B6/SUM($B$3:$B$14),0)
A7: Health | B7: =SUMIFS('💵 Transactions'!$E$3:$E$300,'💵 Transactions'!$C$3:$C$300,$A7,'💵 Transactions'!$D$3:$D$300,"Expense") | C7: =IFERROR(B7/SUM($B$3:$B$14),0)
A8: Entertainment | B8: =SUMIFS('💵 Transactions'!$E$3:$E$300,'💵 Transactions'!$C$3:$C$300,$A8,'💵 Transactions'!$D$3:$D$300,"Expense") | C8: =IFERROR(B8/SUM($B$3:$B$14),0)
A9: Shopping | B9: =SUMIFS('💵 Transactions'!$E$3:$E$300,'💵 Transactions'!$C$3:$C$300,$A9,'💵 Transactions'!$D$3:$D$300,"Expense") | C9: =IFERROR(B9/SUM($B$3:$B$14),0)
A10: Savings | B10: =SUMIFS('💵 Transactions'!$E$3:$E$300,'💵 Transactions'!$C$3:$C$300,$A10,'💵 Transactions'!$D$3:$D$300,"Expense") | C10: =IFERROR(B10/SUM($B$3:$B$14),0)
A11: Debt | B11: =SUMIFS('💵 Transactions'!$E$3:$E$300,'💵 Transactions'!$C$3:$C$300,$A11,'💵 Transactions'!$D$3:$D$300,"Expense") | C11: =IFERROR(B11/SUM($B$3:$B$14),0)
A12: Salary | B12: =SUMIFS('💵 Transactions'!$E$3:$E$300,'💵 Transactions'!$C$3:$C$300,$A12,'💵 Transactions'!$D$3:$D$300,"Expense") | C12: =IFERROR(B12/SUM($B$3:$B$14),0)
A13: Other Income | B13: =SUMIFS('💵 Transactions'!$E$3:$E$300,'💵 Transactions'!$C$3:$C$300,$A13,'💵 Transactions'!$D$3:$D$300,"Expense") | C13: =IFERROR(B13/SUM($B$3:$B$14),0)
A14: Other | B14: =SUMIFS('💵 Transactions'!$E$3:$E$300,'💵 Transactions'!$C$3:$C$300,$A14,'💵 Transactions'!$D$3:$D$300,"Expense") | C14: =IFERROR(B14/SUM($B$3:$B$14),0)
