Workbook

Sheet START HERE
B2: 🏡 AIRBNB HOST REVENUE TRACKER
B4: Short-Term Rental Income & Expense Google Sheets
B6: STEP 1 — Fill in “Bookings”
B7: All guest bookings: dates, nights, revenue, and status.
B9: STEP 2 — Fill in “Expenses”
B10: All property expenses: cleaning, supplies, utilities, maintenance.
B12: STEP 3 — Fill in “Monthly Report”
B13: Month-by-month revenue, expenses, and net profit.
B15: Then open the Dashboard — everything calculates automatically.
B17: TIP: Delete the sample rows once you've seen how it works.
B19: TIP: On Google Sheets? File → Make a copy first, then edit your copy.
B21: TIP: Columns with dropdowns keep your data clean — use them.
B23: Need help? Message NasriTools on Etsy — I reply fast. 🧡

Sheet Bookings
A1: Check-in | B1: Check-out | C1: Nights | D1: Guest | E1: Revenue $ | F1: Platform | G1: Status
A2: 46174 | B2: 46174 | C2: 3 | D2: Alex Martin | E2: 360 | F2: Airbnb | G2: Confirmed
A3: 46180 | B3: 46180 | C3: 2.1 | D3: Sara Lopez | E3: 252 | F3: VRBO | G3: Checked In
A4: 46186 | B4: 46186 | C4: 3.9 | D4: Omar Haddad | E4: 468 | F4: Booking.com | G4: Completed
A5: 46189 | B5: 46189 | C5: 2.55 | D5: Emma Fischer | E5: 306 | F5: Direct | G5: Cancelled
A6: 46195 | B6: 46195 | C6: 3.45 | D6: Liam Carter | E6: 414 | F6: Other | G6: Confirmed
A7: 46201 | B7: 46201 | C7: 1.8 | D7: Nadia Rahali | E7: 216 | F7: Airbnb | G7: Checked In
A8: 46176 | B8: 46176 | C8: 4.35 | D8: Tom Becker | E8: 522 | F8: VRBO | G8: Completed
A9: 46182 | B9: 46182 | C9: 2.85 | D9: Julia Romero | E9: 342 | F9: Booking.com | G9: Cancelled
A10: 46188 | B10: 46188 | C10: 3.75 | D10: Karim Ziani | E10: 450 | F10: Direct | G10: Confirmed
A11: 46191 | B11: 46191 | C11: 2.4 | D11: Anna Kowalska | E11: 288 | F11: Other | G11: Checked In
A12: 46197 | B12: 46197 | C12: 3.3 | D12: David Chen | E12: 396 | F12: Airbnb | G12: Completed
A13: 46175 | B13: 46175 | C13: 2.25 | D13: Lea Moreau | E13: 270 | F13: VRBO | G13: Cancelled

Sheet Dashboard
B2: 📊 AIRBNB HOST REVENUE TRACKER — DASHBOARD
B4: TOTAL REVENUE | D4: OCCUPANCY RATE | F4: TOTAL EXPENSES | H4: NET PROFIT
B5: =SUM(Bookings!E:E) | D5: =TEXT(SUM(Bookings!C:C)/365,"0%") | F5: =SUM(Expenses!C:C) | H5: =SUM(Bookings!E:E)-SUM(Expenses!C:C)
B8: WHAT'S INSIDE
B9: 📅 Bookings — All guest bookings: dates, nights, revenue, and status.
B10: 💸 Expenses — All property expenses: cleaning, supplies, utilities, maintenance.
B11: 📊 Monthly Report — Month-by-month revenue, expenses, and net profit.
B12: 📋 Annual Summary — Annual revenue, expenses, and net income for tax reporting.
B14: Numbers update automatically as you fill the other tabs. Start with sample data deleted.

Sheet Expenses
A1: Date | B1: Description | C1: Amount $ | D1: Category | E1: Deductible
A2: 46174 | B2: Cleaning after checkout | C2: 75 | D2: Cleaning | E2: Yes
A3: 46180 | B3: Cleaning after checkout | C3: 52.5 | D3: Supplies | E3: No
A4: 46186 | C4: 97.5 | D4: Utilities | E4: Partial
A5: 46189 | B5: Cleaning after checkout | C5: 63.75 | D5: Maintenance | E5: Yes
A6: 46195 | B6: Cleaning after checkout | C6: 86.25 | D6: Platform Fee | E6: No
A7: 46201 | C7: 45 | D7: Insurance | E7: Partial
A8: 46176 | B8: Cleaning after checkout | C8: 108.75 | D8: Mortgage | E8: Yes
A9: 46182 | B9: Cleaning after checkout | C9: 71.25 | D9: Other | E9: No
A10: 46188 | C10: 93.75 | D10: Cleaning | E10: Partial
A11: 46191 | B11: Cleaning after checkout | C11: 60 | D11: Supplies | E11: Yes
A12: 46197 | B12: Cleaning after checkout | C12: 82.5 | D12: Utilities | E12: No
A13: 46175 | C13: 56.25 | D13: Maintenance | E13: Partial

Sheet Monthly Report
A1: Month | B1: Bookings | C1: Nights | D1: Revenue $ | E1: Expenses $ | F1: Net $ | G1: Occupancy %
A2: January 2024 | B2: 8 | C2: 22 | D2: 2640 | E2: 900 | F2: =D2-E2 | G2: =TEXT(C2/30,"0%")
A3: January 2025 | B3: 5.6 | C3: 15.4 | D3: 1848 | E3: 630 | F3: =D3-E3 | G3: =TEXT(C3/30,"0%")
A4: January 2026 | B4: 10.4 | C4: 28.6 | D4: 3432 | E4: 1170 | F4: =D4-E4 | G4: =TEXT(C4/30,"0%")
A5: January 2027 | B5: 6.8 | C5: 18.7 | D5: 2244 | E5: 765 | F5: =D5-E5 | G5: =TEXT(C5/30,"0%")
A6: January 2028 | B6: 9.2 | C6: 25.3 | D6: 3036 | E6: 1035 | F6: =D6-E6 | G6: =TEXT(C6/30,"0%")
A7: January 2029 | B7: 4.8 | C7: 13.2 | D7: 1584 | E7: 540 | F7: =D7-E7 | G7: =TEXT(C7/30,"0%")
A8: January 2030 | B8: 11.6 | C8: 31.9 | D8: 3828 | E8: 1305 | F8: =D8-E8 | G8: =TEXT(C8/30,"0%")
A9: January 2031 | B9: 7.6 | C9: 20.9 | D9: 2508 | E9: 855 | F9: =D9-E9 | G9: =TEXT(C9/30,"0%")
A10: January 2032 | B10: 10 | C10: 27.5 | D10: 3300 | E10: 1125 | F10: =D10-E10 | G10: =TEXT(C10/30,"0%")
A11: January 2033 | B11: 6.4 | C11: 17.6 | D11: 2112 | E11: 720 | F11: =D11-E11 | G11: =TEXT(C11/30,"0%")
A12: January 2034 | B12: 8.8 | C12: 24.2 | D12: 2904 | E12: 990 | F12: =D12-E12 | G12: =TEXT(C12/30,"0%")
A13: January 2035 | B13: 6 | C13: 16.5 | D13: 1980 | E13: 675 | F13: =D13-E13 | G13: =TEXT(C13/30,"0%")

Sheet Annual Summary
B2: 📈 ANNUAL SUMMARY
B4: Annual Performance
B5: Total Revenue | C5: =SUM(Bookings!E:E)
B6: Total Expenses | C6: =SUM(Expenses!C:C)
B7: Net Income | C7: =SUM(Bookings!E:E)-SUM(Expenses!C:C)
