Workbook

Sheet START HERE
B2: 💵 DIVIDEND INCOME PORTFOLIO TRACKER
B4: Passive Income & DRIP Investment Google Sheets
B6: STEP 1 — Fill in “Holdings”
B7: All dividend stocks and ETFs with yield and quarterly payment.
B9: STEP 2 — Fill in “Payment Log”
B10: All dividend payments received by date and stock.
B12: STEP 3 — Fill in “Projection”
B13: Dividend income projection over 10 years with DRIP reinvestment.
B15: Then open the Dashboard — everything calculates automatically.
B17: TIP: Delete the sample rows once you've seen how it works.
B19: TIP: On Google Sheets? File → Make a copy first, then edit your copy.
B21: TIP: Columns with dropdowns keep your data clean — use them.
B23: Need help? Message NasriTools on Etsy — I reply fast. 🧡

Sheet Holdings
A1: Ticker | B1: Company | C1: Shares | D1: Price $ | E1: Value $ | F1: Quarterly Div $ | G1: Yield % | H1: Frequency
A2: VYM | B2: BrightWave Studio | C2: 100 | D2: 110 | E2: =C2*D2 | F2: 75 | G2: =TEXT(F2*4/E2,"0.0%") | H2: Quarterly
A3: VYM | B3: GreenLeaf Co. | C3: 70 | D3: 77 | E3: =C3*D3 | F3: 52.5 | G3: =TEXT(F3*4/E3,"0.0%") | H3: Monthly
B4: Nova Digital | C4: 130 | D4: 143 | E4: =C4*D4 | F4: 97.5 | G4: =TEXT(F4*4/E4,"0.0%") | H4: Annual
A5: VYM | B5: Atlas Consulting | C5: 85 | D5: 94 | E5: =C5*D5 | F5: 63.75 | G5: =TEXT(F5*4/E5,"0.0%") | H5: Semi-Annual
A6: VYM | B6: Pixel & Co | C6: 115 | D6: 126 | E6: =C6*D6 | F6: 86.25 | G6: =TEXT(F6*4/E6,"0.0%") | H6: Quarterly
B7: Blue Harbor Ltd | C7: 60 | D7: 66 | E7: =C7*D7 | F7: 45 | G7: =TEXT(F7*4/E7,"0.0%") | H7: Monthly
A8: VYM | B8: Sunrise Media | C8: 145 | D8: 160 | E8: =C8*D8 | F8: 108.75 | G8: =TEXT(F8*4/E8,"0.0%") | H8: Annual
A9: VYM | B9: UrbanCraft | C9: 95 | D9: 104 | E9: =C9*D9 | F9: 71.25 | G9: =TEXT(F9*4/E9,"0.0%") | H9: Semi-Annual
B10: PrimeWorks | C10: 125 | D10: 138 | E10: =C10*D10 | F10: 93.75 | G10: =TEXT(F10*4/E10,"0.0%") | H10: Quarterly
A11: VYM | B11: EchoLab | C11: 80 | D11: 88 | E11: =C11*D11 | F11: 60 | G11: =TEXT(F11*4/E11,"0.0%") | H11: Monthly
A12: VYM | B12: Vertex Group | C12: 110 | D12: 121 | E12: =C12*D12 | F12: 82.5 | G12: =TEXT(F12*4/E12,"0.0%") | H12: Annual
B13: ClearPath Inc | C13: 75 | D13: 82 | E13: =C13*D13 | F13: 56.25 | G13: =TEXT(F13*4/E13,"0.0%") | H13: Semi-Annual

Sheet Dashboard
B2: 📊 DIVIDEND INCOME PORTFOLIO TRACKER — DASHBOARD
B4: ANNUAL DIVIDENDS | D4: MONTHLY AVG | F4: AVG YIELD | H4: TOTAL HOLDINGS
B5: =SUM(Holdings!F:F)*4 | D5: =SUM(Holdings!F:F)*4/12 | F5: =AVERAGE(Holdings!G:G) | H5: =COUNTA(Holdings!A:A)-1
B8: WHAT'S INSIDE
B9: 📊 Holdings — All dividend stocks and ETFs with yield and quarterly payment.
B10: 📅 Payment Log — All dividend payments received by date and stock.
B11: 📈 Projection — Dividend income projection over 10 years with DRIP reinvestment.
B12: 📊 Annual Report — Annual dividend income by stock and month for taxes.
B14: Numbers update automatically as you fill the other tabs. Start with sample data deleted.

Sheet Payment Log
A1: Date | B1: Ticker | C1: Shares | D1: Per Share $ | E1: Total $ | F1: Reinvested
A2: 46174 | B2: VYM | C2: 100 | D2: 0.75 | E2: =C2*D2 | F2: Yes (DRIP)
A3: 46180 | B3: VYM | C3: 70 | D3: 0.52 | E3: =C3*D3 | F3: No (Cash)
A4: 46186 | C4: 130 | D4: 0.98 | E4: =C4*D4 | F4: Yes (DRIP)
A5: 46189 | B5: VYM | C5: 85 | D5: 0.64 | E5: =C5*D5 | F5: No (Cash)
A6: 46195 | B6: VYM | C6: 115 | D6: 0.86 | E6: =C6*D6 | F6: Yes (DRIP)
A7: 46201 | C7: 60 | D7: 0.45 | E7: =C7*D7 | F7: No (Cash)
A8: 46176 | B8: VYM | C8: 145 | D8: 1.09 | E8: =C8*D8 | F8: Yes (DRIP)
A9: 46182 | B9: VYM | C9: 95 | D9: 0.71 | E9: =C9*D9 | F9: No (Cash)
A10: 46188 | C10: 125 | D10: 0.94 | E10: =C10*D10 | F10: Yes (DRIP)
A11: 46191 | B11: VYM | C11: 80 | D11: 0.6 | E11: =C11*D11 | F11: No (Cash)
A12: 46197 | B12: VYM | C12: 110 | D12: 0.83 | E12: =C12*D12 | F12: Yes (DRIP)
A13: 46175 | C13: 75 | D13: 0.56 | E13: =C13*D13 | F13: No (Cash)

Sheet Projection
A1: Year | B1: Portfolio $ | C1: Yield % | D1: Annual Divs $ | E1: Monthly $
A2: 2024 | B2: 50000 | C2: 3.5 | D2: =C2*D2/100 | E2: =E2/12
A3: 1417 | B3: 35000 | C3: 2.45 | D3: =C3*D3/100 | E3: =E3/12
A4: 2631 | B4: 65000 | C4: 4.55 | D4: =C4*D4/100 | E4: =E4/12
A5: 1720 | B5: 42500 | C5: 2.98 | D5: =C5*D5/100 | E5: =E5/12
A6: 2328 | B6: 57500 | C6: 4.02 | D6: =C6*D6/100 | E6: =E6/12
A7: 1214 | B7: 30000 | C7: 2.1 | D7: =C7*D7/100 | E7: =E7/12
A8: 2935 | B8: 72500 | C8: 5.08 | D8: =C8*D8/100 | E8: =E8/12
A9: 1923 | B9: 47500 | C9: 3.32 | D9: =C9*D9/100 | E9: =E9/12
A10: 2530 | B10: 62500 | C10: 4.38 | D10: =C10*D10/100 | E10: =E10/12
A11: 1619 | B11: 40000 | C11: 2.8 | D11: =C11*D11/100 | E11: =E11/12
A12: 2226 | B12: 55000 | C12: 3.85 | D12: =C12*D12/100 | E12: =E12/12
A13: 1518 | B13: 37500 | C13: 2.62 | D13: =C13*D13/100 | E13: =E13/12

Sheet Annual Report
B2: 📈 ANNUAL REPORT
B4: Dividend Summary
B5: Total Dividends Received | C5: =SUM(Payment_Log!E:E)
B6: Annual Projected | C6: =SUM(Holdings!F:F)*4
B7: Monthly Average | C7: =SUM(Holdings!F:F)*4/12
