Workbook

Sheet 📊 Dashboard
B2: 🍽️ RESTAURANT & CAFE MANAGER
B3: Smart Business Automation Template
B5: 💰 TODAY'S SALES | D5: 📦 LOW STOCK ITEMS | F5: 👥 STAFF TODAY
B7: ='📈 Daily Sales'!C32 | D7: ='📦 Inventory'!H2 | F7: ='👥 Staff Schedule'!H2
B10: 📅 WEEKLY SALES SUMMARY
B11: Day | C11: Sales ($) | D11: Expenses ($) | E11: Profit ($) | F11: Orders | G11: Avg Order ($)
B12: Monday | C12: 0 | D12: 0 | E12: =C12-D12 | F12: 0 | G12: =IF(F12=0,0,C12/F12)
B13: Tuesday | C13: 0 | D13: 0 | E13: =C13-D13 | F13: 0 | G13: =IF(F13=0,0,C13/F13)
B14: Wednesday | C14: 0 | D14: 0 | E14: =C14-D14 | F14: 0 | G14: =IF(F14=0,0,C14/F14)
B15: Thursday | C15: 0 | D15: 0 | E15: =C15-D15 | F15: 0 | G15: =IF(F15=0,0,C15/F15)
B16: Friday | C16: 0 | D16: 0 | E16: =C16-D16 | F16: 0 | G16: =IF(F16=0,0,C16/F16)
B17: Saturday | C17: 0 | D17: 0 | E17: =C17-D17 | F17: 0 | G17: =IF(F17=0,0,C17/F17)
B18: Sunday | C18: 0 | D18: 0 | E18: =C18-D18 | F18: 0 | G18: =IF(F18=0,0,C18/F18)
B19: TOTAL | C19: =SUM(C12:C18) | D19: =SUM(D12:D18) | E19: =SUM(E12:E18) | F19: =SUM(F12:F18) | G19: =SUM(G12:G18)
B21: 💡 TIP: Fill yellow cells with your daily data. Green cells calculate automatically.

Sheet 📦 Inventory
B1: 📦 INVENTORY TRACKER
H2: =COUNTIF(F3:F52,"<="&G3:G52)
B3: Item Name | C3: Category | D3: Unit | E3: Current Stock | F3: Min Stock | G3: Status | H3: Unit Cost ($) | I3: Total Value ($)
B4: Coffee Beans | C4: Beverages | D4: kg | E4: 50 | F4: 10 | G4: =IF(E4<=F4,"⚠️ LOW","✅ OK") | H4: 0 | I4: =E4*H4
B5: Milk | C5: Beverages | D5: L | E5: 30 | F5: 10 | G5: =IF(E5<=F5,"⚠️ LOW","✅ OK") | H5: 0 | I5: =E5*H5
B6: Sugar | C6: Dry Goods | D6: kg | E6: 20 | F6: 5 | G6: =IF(E6<=F6,"⚠️ LOW","✅ OK") | H6: 0 | I6: =E6*H6
B7: Flour | C7: Dry Goods | D7: kg | E7: 15 | F7: 5 | G7: =IF(E7<=F7,"⚠️ LOW","✅ OK") | H7: 0 | I7: =E7*H7
B8: Chicken | C8: Proteins | D8: kg | E8: 10 | F8: 3 | G8: =IF(E8<=F8,"⚠️ LOW","✅ OK") | H8: 0 | I8: =E8*H8
B9: Tomatoes | C9: Vegetables | D9: kg | E9: 8 | F9: 3 | G9: =IF(E9<=F9,"⚠️ LOW","✅ OK") | H9: 0 | I9: =E9*H9
B10: Olive Oil | C10: Condiments | D10: L | E10: 5 | F10: 2 | G10: =IF(E10<=F10,"⚠️ LOW","✅ OK") | H10: 0 | I10: =E10*H10
B11: Cheese | C11: Dairy | D11: kg | E11: 6 | F11: 2 | G11: =IF(E11<=F11,"⚠️ LOW","✅ OK") | H11: 0 | I11: =E11*H11
B12: Bread Loaves | C12: Bakery | D12: pcs | E12: 20 | F12: 5 | G12: =IF(E12<=F12,"⚠️ LOW","✅ OK") | H12: 0 | I12: =E12*H12
B13: Disposable Cups | C13: Supplies | D13: pcs | E13: 200 | F13: 50 | G13: =IF(E13<=F13,"⚠️ LOW","✅ OK") | H13: 0 | I13: =E13*H13
G14: =IF(E14="","",IF(E14<=F14,"⚠️ LOW","✅ OK")) | I14: =IF(E14="","",E14*H14)
G15: =IF(E15="","",IF(E15<=F15,"⚠️ LOW","✅ OK")) | I15: =IF(E15="","",E15*H15)
G16: =IF(E16="","",IF(E16<=F16,"⚠️ LOW","✅ OK")) | I16: =IF(E16="","",E16*H16)
G17: =IF(E17="","",IF(E17<=F17,"⚠️ LOW","✅ OK")) | I17: =IF(E17="","",E17*H17)
G18: =IF(E18="","",IF(E18<=F18,"⚠️ LOW","✅ OK")) | I18: =IF(E18="","",E18*H18)
G19: =IF(E19="","",IF(E19<=F19,"⚠️ LOW","✅ OK")) | I19: =IF(E19="","",E19*H19)
G20: =IF(E20="","",IF(E20<=F20,"⚠️ LOW","✅ OK")) | I20: =IF(E20="","",E20*H20)
G21: =IF(E21="","",IF(E21<=F21,"⚠️ LOW","✅ OK")) | I21: =IF(E21="","",E21*H21)
G22: =IF(E22="","",IF(E22<=F22,"⚠️ LOW","✅ OK")) | I22: =IF(E22="","",E22*H22)
G23: =IF(E23="","",IF(E23<=F23,"⚠️ LOW","✅ OK")) | I23: =IF(E23="","",E23*H23)
G24: =IF(E24="","",IF(E24<=F24,"⚠️ LOW","✅ OK")) | I24: =IF(E24="","",E24*H24)
G25: =IF(E25="","",IF(E25<=F25,"⚠️ LOW","✅ OK")) | I25: =IF(E25="","",E25*H25)
... G52: =IF(E52="","",IF(E52<=F52,"⚠️ LOW","✅ OK")) | I52: =IF(E52="","",E52*H52)
B54: TOTAL INVENTORY VALUE | I54: =SUM(I4:I53)

Sheet 📈 Daily Sales
B1: 📈 DAILY SALES TRACKER
B3: # | C3: Item / Service | D3: Category | E3: Qty | F3: Price ($) | G3: Total ($) | H3: Payment | I3: Time
B4: 1 | E4: 0 | F4: 0 | G4: =IF(E4=0,"",E4*F4)
B5: 2 | E5: 0 | F5: 0 | G5: =IF(E5=0,"",E5*F5)
B6: 3 | E6: 0 | F6: 0 | G6: =IF(E6=0,"",E6*F6)
B7: 4 | E7: 0 | F7: 0 | G7: =IF(E7=0,"",E7*F7)
B8: 5 | E8: 0 | F8: 0 | G8: =IF(E8=0,"",E8*F8)
B9: 6 | E9: 0 | F9: 0 | G9: =IF(E9=0,"",E9*F9)
B10: 7 | E10: 0 | F10: 0 | G10: =IF(E10=0,"",E10*F10)
B11: 8 | E11: 0 | F11: 0 | G11: =IF(E11=0,"",E11*F11)
B12: 9 | E12: 0 | F12: 0 | G12: =IF(E12=0,"",E12*F12)
B13: 10 | E13: 0 | F13: 0 | G13: =IF(E13=0,"",E13*F13)
B14: 11 | E14: 0 | F14: 0 | G14: =IF(E14=0,"",E14*F14)
B15: 12 | E15: 0 | F15: 0 | G15: =IF(E15=0,"",E15*F15)
... B31: 28 | E31: 0 | F31: 0 | G31: =IF(E31=0,"",E31*F31)
C32: =SUM(E4:E31)
C33: DAILY TOTAL | G33: =SUM(G4:G31)

Sheet 👥 Staff Schedule
B1: 👥 STAFF WEEKLY SCHEDULE
H2: =COUNTIF(C4:C13,"Working")
B3: Staff Name | C3: Role | D3: Mon | E3: Tue | F3: Wed | G3: Thu | H3: Fri | I3: Sat | J3: Sun | K3: Total Hours
B4: Ahmed Ali | C4: Manager | D4: Working | E4: Working | F4: Working | G4: Working | H4: Working | I4: Off | J4: Off | K4: =COUNTIF(D4:J4,"Working")*8+COUNTIF(D4:J4,"Half Day")*4
B5: Sara Mohamed | C5: Cashier | D5: Working | E5: Working | F5: Working | G5: Working | H5: Working | I5: Off | J5: Off | K5: =COUNTIF(D5:J5,"Working")*8+COUNTIF(D5:J5,"Half Day")*4
B6: Omar Hassan | C6: Chef | D6: Working | E6: Working | F6: Working | G6: Working | H6: Working | I6: Off | J6: Off | K6: =COUNTIF(D6:J6,"Working")*8+COUNTIF(D6:J6,"Half Day")*4
B7: Layla Khalid | C7: Barista | D7: Working | E7: Working | F7: Working | G7: Working | H7: Working | I7: Off | J7: Off | K7: =COUNTIF(D7:J7,"Working")*8+COUNTIF(D7:J7,"Half Day")*4
B8: Yusuf Salem | C8: Waiter | D8: Working | E8: Working | F8: Working | G8: Working | H8: Working | I8: Off | J8: Off | K8: =COUNTIF(D8:J8,"Working")*8+COUNTIF(D8:J8,"Half Day")*4
B9: Nour Ibrahim | C9: Waiter | D9: Working | E9: Working | F9: Working | G9: Working | H9: Working | I9: Off | J9: Off | K9: =COUNTIF(D9:J9,"Working")*8+COUNTIF(D9:J9,"Half Day")*4
B10: Kareem Tarek | C10: Delivery | D10: Working | E10: Working | F10: Working | G10: Working | H10: Working | I10: Off | J10: Off | K10: =COUNTIF(D10:J10,"Working")*8+COUNTIF(D10:J10,"Half Day")*4
B11: Hana Adel | C11: Cashier | D11: Working | E11: Working | F11: Working | G11: Working | H11: Working | I11: Off | J11: Off | K11: =COUNTIF(D11:J11,"Working")*8+COUNTIF(D11:J11,"Half Day")*4
B13: WEEKLY TOTALS | K13: =SUM(K4:K12)

Sheet 📊 Reports
B1: 📊 AUTOMATED REPORTS
B3: 💰 PROFIT & LOSS SUMMARY (WEEKLY)
B4: Total Revenue | C4: ='📊 Dashboard'!C19
B5: Total Expenses | C5: ='📊 Dashboard'!D19
B6: Gross Profit | C6: =C4-C5
B7: Inventory Value | C7: ='📦 Inventory'!I54
B8: Net Profit | C8: =C6-C7
B9: Profit Margin % | C9: =IF(C4=0,0,C8/C4*100)
B11: 📈 PERFORMANCE INDICATORS
B12: Best Day Sales | C12: =MAX('📊 Dashboard'!C12:C18)
B13: Worst Day Sales | C13: =MIN(IF('📊 Dashboard'!C12:C18>0,'📊 Dashboard'!C12:C18))
B14: Avg Daily Sales | C14: =AVERAGE('📊 Dashboard'!C12:C18)
B15: Total Orders | C15: =SUM('📊 Dashboard'!F12:F18)
B16: Avg Order Value | C16: =IFERROR(C14/C15,0)
B17: Low Stock Items | C17: ='📦 Inventory'!H2
B19: 💡 QUICK TIPS
B20: ✅ Update Daily Sales tab every day for accurate reports
B21: ✅ Check Inventory tab weekly to avoid running out of stock
B22: ✅ Review this Reports tab every Monday for weekly insights
B23: ✅ Yellow cells = input | Green cells = auto-calculated
B24: ✅ Share this file with your team via Google Sheets
