Workbook

Sheet Dashboard
A1: Amazon FBA Product Tracker
A3: Total Revenue | B3: Total Profit | C3: Overall ACOS | D3: Avg Margin
A4: =SUM(Products!D:D) | B4: =SUM(Products!H:H) | C4: =TEXT(SUM(PPC!C:C)/SUM(Products!D:D),"0.0%") | D4: =TEXT(SUM(Products!H:H)/SUM(Products!D:D),"0.0%")

Sheet Products
A1: ASIN | B1: Product Name | C1: Units Sold | D1: Revenue $ | E1: COGS $ | F1: Amazon Fee $ | G1: PPC Spend $ | H1: Net Profit $
A2: B09XYZ1234 | B2: Kitchen Organizer Set | C2: 230 | D2: 3450 | E2: 690 | F2: 518 | G2: 345 | H2: =D2-E2-F2-G2
A3: B09XYZ1234 | B3: Kitchen Organizer Set | C3: 230 | D3: 3450 | E3: 690 | F3: 518 | G3: 345 | H3: =D3-E3-F3-G3
A4: B09XYZ1234 | B4: Kitchen Organizer Set | C4: 230 | D4: 3450 | E4: 690 | F4: 518 | G4: 345 | H4: =D4-E4-F4-G4
A5: B09XYZ1234 | B5: Kitchen Organizer Set | C5: 230 | D5: 3450 | E5: 690 | F5: 518 | G5: 345 | H5: =D5-E5-F5-G5
A6: B09XYZ1234 | B6: Kitchen Organizer Set | C6: 230 | D6: 3450 | E6: 690 | F6: 518 | G6: 345 | H6: =D6-E6-F6-G6
A7: B09XYZ1234 | B7: Kitchen Organizer Set | C7: 230 | D7: 3450 | E7: 690 | F7: 518 | G7: 345 | H7: =D7-E7-F7-G7
A8: B09XYZ1234 | B8: Kitchen Organizer Set | C8: 230 | D8: 3450 | E8: 690 | F8: 518 | G8: 345 | H8: =D8-E8-F8-G8
A9: B09XYZ1234 | B9: Kitchen Organizer Set | C9: 230 | D9: 3450 | E9: 690 | F9: 518 | G9: 345 | H9: =D9-E9-F9-G9
A10: B09XYZ1234 | B10: Kitchen Organizer Set | C10: 230 | D10: 3450 | E10: 690 | F10: 518 | G10: 345 | H10: =D10-E10-F10-G10
A11: B09XYZ1234 | B11: Kitchen Organizer Set | C11: 230 | D11: 3450 | E11: 690 | F11: 518 | G11: 345 | H11: =D11-E11-F11-G11
A12: B09XYZ1234 | B12: Kitchen Organizer Set | C12: 230 | D12: 3450 | E12: 690 | F12: 518 | G12: 345 | H12: =D12-E12-F12-G12
A13: B09XYZ1234 | B13: Kitchen Organizer Set | C13: 230 | D13: 3450 | E13: 690 | F13: 518 | G13: 345 | H13: =D13-E13-F13-G13
... A16: B09XYZ1234 | B16: Kitchen Organizer Set | C16: 230 | D16: 3450 | E16: 690 | F16: 518 | G16: 345 | H16: =D16-E16-F16-G16

Sheet Inventory
A1: Product | B1: ASIN | C1: Units In FBA | D1: Units Ordered | E1: Reorder Point | F1: Status
A2: Kitchen Organizer Set | B2: B09XYZ1234 | C2: 85 | D2: 200 | E2: 50
A3: Kitchen Organizer Set | B3: B09XYZ1234 | C3: 85 | D3: 200 | E3: 50
A4: Kitchen Organizer Set | B4: B09XYZ1234 | C4: 85 | D4: 200 | E4: 50
A5: Kitchen Organizer Set | B5: B09XYZ1234 | C5: 85 | D5: 200 | E5: 50
A6: Kitchen Organizer Set | B6: B09XYZ1234 | C6: 85 | D6: 200 | E6: 50
A7: Kitchen Organizer Set | B7: B09XYZ1234 | C7: 85 | D7: 200 | E7: 50
A8: Kitchen Organizer Set | B8: B09XYZ1234 | C8: 85 | D8: 200 | E8: 50
A9: Kitchen Organizer Set | B9: B09XYZ1234 | C9: 85 | D9: 200 | E9: 50
A10: Kitchen Organizer Set | B10: B09XYZ1234 | C10: 85 | D10: 200 | E10: 50
A11: Kitchen Organizer Set | B11: B09XYZ1234 | C11: 85 | D11: 200 | E11: 50
A12: Kitchen Organizer Set | B12: B09XYZ1234 | C12: 85 | D12: 200 | E12: 50
A13: Kitchen Organizer Set | B13: B09XYZ1234 | C13: 85 | D13: 200 | E13: 50
... A16: Kitchen Organizer Set | B16: B09XYZ1234 | C16: 85 | D16: 200 | E16: 50

Sheet PPC
A1: Campaign | B1: Product | C1: Spend $ | D1: PPC Sales $ | E1: ACOS % | F1: ROAS | G1: Status
A2: Kitchen Set - Auto | B2: Kitchen Organizer Set | C2: 345 | D2: 1150 | E2: =TEXT(C2/D2,"0.0%") | F2: =D2/C2
A3: Kitchen Set - Auto | B3: Kitchen Organizer Set | C3: 345 | D3: 1150 | E3: =TEXT(C3/D3,"0.0%") | F3: =D3/C3
A4: Kitchen Set - Auto | B4: Kitchen Organizer Set | C4: 345 | D4: 1150 | E4: =TEXT(C4/D4,"0.0%") | F4: =D4/C4
A5: Kitchen Set - Auto | B5: Kitchen Organizer Set | C5: 345 | D5: 1150 | E5: =TEXT(C5/D5,"0.0%") | F5: =D5/C5
A6: Kitchen Set - Auto | B6: Kitchen Organizer Set | C6: 345 | D6: 1150 | E6: =TEXT(C6/D6,"0.0%") | F6: =D6/C6
A7: Kitchen Set - Auto | B7: Kitchen Organizer Set | C7: 345 | D7: 1150 | E7: =TEXT(C7/D7,"0.0%") | F7: =D7/C7
A8: Kitchen Set - Auto | B8: Kitchen Organizer Set | C8: 345 | D8: 1150 | E8: =TEXT(C8/D8,"0.0%") | F8: =D8/C8
A9: Kitchen Set - Auto | B9: Kitchen Organizer Set | C9: 345 | D9: 1150 | E9: =TEXT(C9/D9,"0.0%") | F9: =D9/C9
A10: Kitchen Set - Auto | B10: Kitchen Organizer Set | C10: 345 | D10: 1150 | E10: =TEXT(C10/D10,"0.0%") | F10: =D10/C10
A11: Kitchen Set - Auto | B11: Kitchen Organizer Set | C11: 345 | D11: 1150 | E11: =TEXT(C11/D11,"0.0%") | F11: =D11/C11

Sheet P&L Report
A1: Reports — Auto-Generated
A3: FBA Business Summary
A4: Total Revenue | B4: =SUM(Products!D:D)
A5: Total COGS | B5: =SUM(Products!E:E)
A6: Net Profit | B6: =SUM(Products!H:H)
