Workbook

Sheet START HERE
B2: ⛪ CHURCH BUDGET & MINISTRY PLANNER
B4: Tithes, Expenses & Ministry Budget Google Sheets
B6: STEP 1 — Fill in “Income”
B7: All church income: tithes, offerings, donations, events.
B9: STEP 2 — Fill in “Expenses”
B10: All church expenses by ministry and category.
B12: STEP 3 — Fill in “Ministry Budgets”
B13: Annual budget allocation by ministry department.
B15: Then open the Dashboard — everything calculates automatically.
B17: TIP: Delete the sample rows once you've seen how it works.
B19: TIP: On Google Sheets? File → Make a copy first, then edit your copy.
B21: TIP: Columns with dropdowns keep your data clean — use them.
B23: Need help? Message NasriTools on Etsy — I reply fast. 🧡

Sheet Income
A1: Date | B1: Type | C1: Amount $ | D1: Notes
A2: 46174 | B2: Sunday Tithes | C2: 3200
A3: 46180 | B3: Special Offering | C3: 2240 | D3: Paid
A4: 46186 | B4: Building Fund | C4: 4160 | D4: Urgent
A5: 46189 | B5: Missions | C5: 2720 | D5: Follow up Friday
A6: 46195 | B6: Event Revenue | C6: 3680
A7: 46201 | B7: Donation | C7: 1920 | D7: Monthly
A8: 46176 | B8: Grant | C8: 4640 | D8: Confirmed
A9: 46182 | B9: Other | C9: 3040
A10: 46188 | B10: Sunday Tithes | C10: 4000 | D10: Waiting reply
A11: 46191 | B11: Special Offering | C11: 2560 | D11: Done early
A12: 46197 | B12: Building Fund | C12: 3520
A13: 46175 | B13: Missions | C13: 2400 | D13: Recheck

Sheet Dashboard
B2: 📊 CHURCH BUDGET & MINISTRY PLANNER — DASHBOARD
B4: WEEKLY INCOME $ | D4: MONTHLY INCOME $ | F4: TOTAL EXPENSES $ | H4: SURPLUS $
B5: =SUM(Income!C:C)/52 | D5: =SUM(Income!C:C)/12 | F5: =SUM(Expenses!D:D) | H5: =SUM(Income!C:C)-SUM(Expenses!D:D)
B8: WHAT'S INSIDE
B9: 💰 Income — All church income: tithes, offerings, donations, events.
B10: 💸 Expenses — All church expenses by ministry and category.
B11: 📋 Ministry Budgets — Annual budget allocation by ministry department.
B12: 📊 Annual Report — Annual financial report for board and congregation.
B14: Numbers update automatically as you fill the other tabs. Start with sample data deleted.

Sheet Expenses
A1: Date | B1: Description | C1: Ministry | D1: Amount $ | E1: Approved By
A2: 46174 | B2: Sound system maintenance | C2: General Operations | D2: 450 | E2: Treasurer
A3: 46180 | B3: Sound system maintenance | C3: Worship | D3: 315 | E3: Treasurer
A4: 46186 | C4: Youth | D4: 585
A5: 46189 | B5: Sound system maintenance | C5: Children | D5: 382 | E5: Treasurer
A6: 46195 | B6: Sound system maintenance | C6: Missions | D6: 518 | E6: Treasurer
A7: 46201 | C7: Building | D7: 270
A8: 46176 | B8: Sound system maintenance | C8: Outreach | D8: 652 | E8: Treasurer
A9: 46182 | B9: Sound system maintenance | C9: Admin | D9: 428 | E9: Treasurer
A10: 46188 | C10: Staff | D10: 562
A11: 46191 | B11: Sound system maintenance | C11: General Operations | D11: 360 | E11: Treasurer
A12: 46197 | B12: Sound system maintenance | C12: Worship | D12: 495 | E12: Treasurer
A13: 46175 | C13: Youth | D13: 338

Sheet Ministry Budgets
A1: Ministry | B1: Annual Budget $ | C1: Spent YTD $ | D1: Remaining $ | E1: Used %
A2: Youth Ministry | B2: 8000 | C2: 3200 | D2: =C2-D2 | E2: =TEXT(D2/C2,"0%")
A3: Youth Ministry | B3: 5600 | C3: 2240 | D3: =C3-D3 | E3: =TEXT(D3/C3,"0%")
B4: 10400 | C4: 4160 | D4: =C4-D4 | E4: =TEXT(D4/C4,"0%")
A5: Youth Ministry | B5: 6800 | C5: 2720 | D5: =C5-D5 | E5: =TEXT(D5/C5,"0%")
A6: Youth Ministry | B6: 9200 | C6: 3680 | D6: =C6-D6 | E6: =TEXT(D6/C6,"0%")
B7: 4800 | C7: 1920 | D7: =C7-D7 | E7: =TEXT(D7/C7,"0%")
A8: Youth Ministry | B8: 11600 | C8: 4640 | D8: =C8-D8 | E8: =TEXT(D8/C8,"0%")
A9: Youth Ministry | B9: 7600 | C9: 3040 | D9: =C9-D9 | E9: =TEXT(D9/C9,"0%")
B10: 10000 | C10: 4000 | D10: =C10-D10 | E10: =TEXT(D10/C10,"0%")
A11: Youth Ministry | B11: 6400 | C11: 2560 | D11: =C11-D11 | E11: =TEXT(D11/C11,"0%")
A12: Youth Ministry | B12: 8800 | C12: 3520 | D12: =C12-D12 | E12: =TEXT(D12/C12,"0%")
B13: 6000 | C13: 2400 | D13: =C13-D13 | E13: =TEXT(D13/C13,"0%")

Sheet Annual Report
B2: 📈 ANNUAL REPORT
B4: Annual Financial Summary
B5: Total Income | C5: =SUM(Income!C:C)
B6: Total Expenses | C6: =SUM(Expenses!D:D)
B7: Net Surplus | C7: =SUM(Income!C:C)-SUM(Expenses!D:D)
