Workbook

Sheet Deal Analyzer
A1: Real Estate Deal Analyzer
A3: Monthly Cash Flow | B3: Annual ROI % | C3: Cap Rate | D3: GRM
A4: =Income!B20-Expenses!B25 | B4: =TEXT(B4*12/Financing!B15,"0.0%") | C4: =TEXT((Income!B20-Expenses!B25)*12/Purchase!B5,"0.0%") | D4: =Purchase!B5/(Income!B20*12)

Sheet Purchase Info
A1: Item | B1: Value | C1: Notes
A2: Purchase Price | B2: 250000 | C2: Negotiated price
A3: Purchase Price | B3: 250000 | C3: Negotiated price
A4: Purchase Price | B4: 250000 | C4: Negotiated price
A5: Purchase Price | B5: 250000 | C5: Negotiated price
A6: Purchase Price | B6: 250000 | C6: Negotiated price
A7: Purchase Price | B7: 250000 | C7: Negotiated price
A8: Purchase Price | B8: 250000 | C8: Negotiated price
A9: Purchase Price | B9: 250000 | C9: Negotiated price

Sheet Income
A1: Income Source | B1: Monthly $ | C1: Annual $ | D1: Notes
A2: Monthly Rent | B2: 1800 | C2: =C2*12 | D2: Unit 1
A3: Monthly Rent | B3: 1800 | C3: =C3*12 | D3: Unit 1
A4: Monthly Rent | B4: 1800 | C4: =C4*12 | D4: Unit 1
A5: Monthly Rent | B5: 1800 | C5: =C5*12 | D5: Unit 1
A6: Monthly Rent | B6: 1800 | C6: =C6*12 | D6: Unit 1
A7: Monthly Rent | B7: 1800 | C7: =C7*12 | D7: Unit 1

Sheet Expenses
A1: Expense | B1: Monthly $ | C1: Annual $ | D1: Category
A2: Mortgage Payment | B2: 900 | C2: =C2*12
A3: Mortgage Payment | B3: 900 | C3: =C3*12
A4: Mortgage Payment | B4: 900 | C4: =C4*12
A5: Mortgage Payment | B5: 900 | C5: =C5*12
A6: Mortgage Payment | B6: 900 | C6: =C6*12
A7: Mortgage Payment | B7: 900 | C7: =C7*12
A8: Mortgage Payment | B8: 900 | C8: =C8*12
A9: Mortgage Payment | B9: 900 | C9: =C9*12
A10: Mortgage Payment | B10: 900 | C10: =C10*12
A11: Mortgage Payment | B11: 900 | C11: =C11*12

Sheet Financing
A1: Item | B1: Value | C1: Notes
A2: Loan Amount | B2: 200000 | C2: 30-year fixed
A3: Loan Amount | B3: 200000 | C3: 30-year fixed
A4: Loan Amount | B4: 200000 | C4: 30-year fixed
A5: Loan Amount | B5: 200000 | C5: 30-year fixed
A6: Loan Amount | B6: 200000 | C6: 30-year fixed
A7: Loan Amount | B7: 200000 | C7: 30-year fixed

Sheet Comparison
A1: Metric | B1: Property 1 | C1: Property 2 | D1: Property 3 | E1: Best
A2: Purchase Price | B2: 250000 | C2: 320000 | D2: 180000 | E2: =MIN(C2:E2)
A3: Purchase Price | B3: 250000 | C3: 320000 | D3: 180000 | E3: =MIN(C3:E3)
A4: Purchase Price | B4: 250000 | C4: 320000 | D4: 180000 | E4: =MIN(C4:E4)
A5: Purchase Price | B5: 250000 | C5: 320000 | D5: 180000 | E5: =MIN(C5:E5)
A6: Purchase Price | B6: 250000 | C6: 320000 | D6: 180000 | E6: =MIN(C6:E6)
A7: Purchase Price | B7: 250000 | C7: 320000 | D7: 180000 | E7: =MIN(C7:E7)
A8: Purchase Price | B8: 250000 | C8: 320000 | D8: 180000 | E8: =MIN(C8:E8)
A9: Purchase Price | B9: 250000 | C9: 320000 | D9: 180000 | E9: =MIN(C9:E9)

Sheet Reports
A1: Reports — Auto-Generated
A3: Deal Summary
A4: Monthly Cash Flow | B4: =Income!C20-Expenses!C25
A5: Annual Cash Flow | B5: =(Income!C20-Expenses!C25)*12
A6: Total Investment | B6: =SUM(Purchase!C:C)
