Workbook

Sheet START HERE
B2: 📈 STOCK INVESTMENT PORTFOLIO TRACKER
B4: Stocks, ETFs & Dividend Tracker Google Sheets
B6: STEP 1 — Fill in “Holdings”
B7: All stock and ETF positions with cost basis and current value.
B9: STEP 2 — Fill in “Transactions”
B10: All buy and sell transactions with dates and fees.
B12: STEP 3 — Fill in “Dividends”
B13: Dividend income tracker: all payments by stock and date.
B15: Then open the Dashboard — everything calculates automatically.
B17: TIP: Delete the sample rows once you've seen how it works.
B19: TIP: On Google Sheets? File → Make a copy first, then edit your copy.
B21: TIP: Columns with dropdowns keep your data clean — use them.
B23: Need help? Message NasriTools on Etsy — I reply fast. 🧡

Sheet Holdings
A1: Ticker | B1: Company | C1: Shares | D1: Avg Cost $ | E1: Current $ | F1: Value $ | G1: Return $ | H1: Type
A2: AAPL | B2: BrightWave Studio | C2: 10 | D2: 145 | E2: 175 | F2: =C2*E2 | G2: =(E2-D2)*C2 | H2: Stock
A3: AAPL | B3: GreenLeaf Co. | C3: 7 | D3: 102 | E3: 122 | F3: =C3*E3 | G3: =(E3-D3)*C3 | H3: ETF
B4: Nova Digital | C4: 13 | D4: 188 | E4: 228 | F4: =C4*E4 | G4: =(E4-D4)*C4 | H4: REIT
A5: AAPL | B5: Atlas Consulting | C5: 8.5 | D5: 123 | E5: 149 | F5: =C5*E5 | G5: =(E5-D5)*C5 | H5: Bond
A6: AAPL | B6: Pixel & Co | C6: 11.5 | D6: 167 | E6: 201 | F6: =C6*E6 | G6: =(E6-D6)*C6 | H6: Mutual Fund
B7: Blue Harbor Ltd | C7: 6 | D7: 87 | E7: 105 | F7: =C7*E7 | G7: =(E7-D7)*C7 | H7: Stock
A8: AAPL | B8: Sunrise Media | C8: 14.5 | D8: 210 | E8: 254 | F8: =C8*E8 | G8: =(E8-D8)*C8 | H8: ETF
A9: AAPL | B9: UrbanCraft | C9: 9.5 | D9: 138 | E9: 166 | F9: =C9*E9 | G9: =(E9-D9)*C9 | H9: REIT
B10: PrimeWorks | C10: 12.5 | D10: 181 | E10: 219 | F10: =C10*E10 | G10: =(E10-D10)*C10 | H10: Bond
A11: AAPL | B11: EchoLab | C11: 8 | D11: 116 | E11: 140 | F11: =C11*E11 | G11: =(E11-D11)*C11 | H11: Mutual Fund
A12: AAPL | B12: Vertex Group | C12: 11 | D12: 160 | E12: 193 | F12: =C12*E12 | G12: =(E12-D12)*C12 | H12: Stock
B13: ClearPath Inc | C13: 7.5 | D13: 109 | E13: 131 | F13: =C13*E13 | G13: =(E13-D13)*C13 | H13: ETF

Sheet Dashboard
B2: 📊 STOCK INVESTMENT PORTFOLIO TRACKER — DASHBOARD
B4: PORTFOLIO VALUE | D4: TOTAL INVESTED | F4: TOTAL RETURN $ | H4: RETURN %
B5: =SUMPRODUCT(Holdings!C:C,Holdings!F:F) | D5: =SUMPRODUCT(Holdings!C:C,Holdings!D:D) | F5: =B4-C4 | H5: =TEXT((B4-C4)/C4,"0.0%")
B8: WHAT'S INSIDE
B9: 💹 Holdings — All stock and ETF positions with cost basis and current value.
B10: 📋 Transactions — All buy and sell transactions with dates and fees.
B11: 💵 Dividends — Dividend income tracker: all payments by stock and date.
B12: 📊 Performance — Annual returns, dividend income, and sector allocation.
B14: Numbers update automatically as you fill the other tabs. Start with sample data deleted.

Sheet Transactions
A1: Date | B1: Ticker | C1: Action | D1: Shares | E1: Price $ | F1: Total $ | G1: Broker
A2: 46174 | B2: MSFT | C2: Buy | D2: 5 | E2: 380 | F2: =D2*E2 | G2: Fidelity
A3: 46180 | B3: MSFT | C3: Sell | D3: 3.5 | E3: 266 | F3: =D3*E3 | G3: Schwab
A4: 46186 | C4: Dividend | D4: 6.5 | E4: 494 | F4: =D4*E4 | G4: Vanguard
A5: 46189 | B5: MSFT | C5: Split | D5: 4.25 | E5: 323 | F5: =D5*E5 | G5: Robinhood
A6: 46195 | B6: MSFT | C6: DRIP | D6: 5.75 | E6: 437 | F6: =D6*E6 | G6: TD Ameritrade
A7: 46201 | C7: Buy | D7: 3 | E7: 228 | F7: =D7*E7 | G7: Other
A8: 46176 | B8: MSFT | C8: Sell | D8: 7.25 | E8: 551 | F8: =D8*E8 | G8: Fidelity
A9: 46182 | B9: MSFT | C9: Dividend | D9: 4.75 | E9: 361 | F9: =D9*E9 | G9: Schwab
A10: 46188 | C10: Split | D10: 6.25 | E10: 475 | F10: =D10*E10 | G10: Vanguard
A11: 46191 | B11: MSFT | C11: DRIP | D11: 4 | E11: 304 | F11: =D11*E11 | G11: Robinhood
A12: 46197 | B12: MSFT | C12: Buy | D12: 5.5 | E12: 418 | F12: =D12*E12 | G12: TD Ameritrade
A13: 46175 | C13: Sell | D13: 3.75 | E13: 285 | F13: =D13*E13 | G13: Other

Sheet Dividends
A1: Date | B1: Ticker | C1: Per Share $ | D1: Shares | E1: Total $ | F1: Reinvested
A2: 46174 | B2: VTI | C2: 0.85 | D2: 50 | E2: =C2*D2 | F2: Yes
A3: 46180 | B3: VTI | C3: 0.59 | D3: 35 | E3: =C3*D3 | F3: No
A4: 46186 | C4: 1.1 | D4: 65 | E4: =C4*D4 | F4: Yes
A5: 46189 | B5: VTI | C5: 0.72 | D5: 42.5 | E5: =C5*D5 | F5: No
A6: 46195 | B6: VTI | C6: 0.98 | D6: 57.5 | E6: =C6*D6 | F6: Yes
A7: 46201 | C7: 0.51 | D7: 30 | E7: =C7*D7 | F7: No
A8: 46176 | B8: VTI | C8: 1.23 | D8: 72.5 | E8: =C8*D8 | F8: Yes
A9: 46182 | B9: VTI | C9: 0.81 | D9: 47.5 | E9: =C9*D9 | F9: No
A10: 46188 | C10: 1.06 | D10: 62.5 | E10: =C10*D10 | F10: Yes
A11: 46191 | B11: VTI | C11: 0.68 | D11: 40 | E11: =C11*D11 | F11: No
A12: 46197 | B12: VTI | C12: 0.94 | D12: 55 | E12: =C12*D12 | F12: Yes
A13: 46175 | C13: 0.64 | D13: 37.5 | E13: =C13*D13 | F13: No

Sheet Performance
B2: 📈 PERFORMANCE
B4: Portfolio Summary
B5: Total Invested | C5: =SUMPRODUCT(Holdings!C:C,Holdings!D:D)
B6: Current Value | C6: =SUMPRODUCT(Holdings!C:C,Holdings!F:F)
B7: Total Dividends | C7: =SUM(Dividends!E:E)
