Workbook

Sheet Dashboard
A1: Net Worth Tracker
A3: Total Assets | B3: Total Liabilities | C3: Net Worth | D3: Debt Ratio
A4: =SUM(Assets!C:C) | B4: =SUM(Liabilities!C:C) | C4: =SUM(Assets!C:C)-SUM(Liabilities!C:C) | D4: =TEXT(SUM(Liabilities!C:C)/SUM(Assets!C:C),"0%")

Sheet Assets
A1: Asset | B1: Category | C1: Value $ | D1: Last Updated | E1: Notes
A2: Savings Account | C2: 15000 | D2: 2024-01-01 | E2: Chase savings account
A3: Savings Account | C3: 15000 | D3: 2024-01-01 | E3: Chase savings account
A4: Savings Account | C4: 15000 | D4: 2024-01-01 | E4: Chase savings account
A5: Savings Account | C5: 15000 | D5: 2024-01-01 | E5: Chase savings account
A6: Savings Account | C6: 15000 | D6: 2024-01-01 | E6: Chase savings account
A7: Savings Account | C7: 15000 | D7: 2024-01-01 | E7: Chase savings account
A8: Savings Account | C8: 15000 | D8: 2024-01-01 | E8: Chase savings account
A9: Savings Account | C9: 15000 | D9: 2024-01-01 | E9: Chase savings account
A10: Savings Account | C10: 15000 | D10: 2024-01-01 | E10: Chase savings account
A11: Savings Account | C11: 15000 | D11: 2024-01-01 | E11: Chase savings account
A12: Savings Account | C12: 15000 | D12: 2024-01-01 | E12: Chase savings account
A13: Savings Account | C13: 15000 | D13: 2024-01-01 | E13: Chase savings account

Sheet Liabilities
A1: Liability | B1: Category | C1: Balance $ | D1: Interest % | E1: Notes
A2: Mortgage | C2: 185000 | D2: 6.5 | E2: 30-year fixed mortgage
A3: Mortgage | C3: 185000 | D3: 6.5 | E3: 30-year fixed mortgage
A4: Mortgage | C4: 185000 | D4: 6.5 | E4: 30-year fixed mortgage
A5: Mortgage | C5: 185000 | D5: 6.5 | E5: 30-year fixed mortgage
A6: Mortgage | C6: 185000 | D6: 6.5 | E6: 30-year fixed mortgage
A7: Mortgage | C7: 185000 | D7: 6.5 | E7: 30-year fixed mortgage
A8: Mortgage | C8: 185000 | D8: 6.5 | E8: 30-year fixed mortgage
A9: Mortgage | C9: 185000 | D9: 6.5 | E9: 30-year fixed mortgage

Sheet Monthly Trend
A1: Month | B1: Assets $ | C1: Liabilities $ | D1: Net Worth $ | E1: Change $
A2: January 2024 | B2: 250000 | C2: 195000 | D2: =C2-D2 | E2: =E2-E{ROW-1}
A3: January 2024 | B3: 250000 | C3: 195000 | D3: =C3-D3 | E3: =E3-E{ROW-1}
A4: January 2024 | B4: 250000 | C4: 195000 | D4: =C4-D4 | E4: =E4-E{ROW-1}
A5: January 2024 | B5: 250000 | C5: 195000 | D5: =C5-D5 | E5: =E5-E{ROW-1}
A6: January 2024 | B6: 250000 | C6: 195000 | D6: =C6-D6 | E6: =E6-E{ROW-1}
A7: January 2024 | B7: 250000 | C7: 195000 | D7: =C7-D7 | E7: =E7-E{ROW-1}
A8: January 2024 | B8: 250000 | C8: 195000 | D8: =C8-D8 | E8: =E8-E{ROW-1}
A9: January 2024 | B9: 250000 | C9: 195000 | D9: =C9-D9 | E9: =E9-E{ROW-1}
A10: January 2024 | B10: 250000 | C10: 195000 | D10: =C10-D10 | E10: =E10-E{ROW-1}
A11: January 2024 | B11: 250000 | C11: 195000 | D11: =C11-D11 | E11: =E11-E{ROW-1}
A12: January 2024 | B12: 250000 | C12: 195000 | D12: =C12-D12 | E12: =E12-E{ROW-1}
A13: January 2024 | B13: 250000 | C13: 195000 | D13: =C13-D13 | E13: =E13-E{ROW-1}

Sheet Summary
A1: Reports — Auto-Generated
A3: Wealth Summary
A4: Total Assets | B4: =SUM(Assets!C:C)
A5: Total Liabilities | B5: =SUM(Liabilities!C:C)
A6: Net Worth | B6: =SUM(Assets!C:C)-SUM(Liabilities!C:C)
