Workbook

Sheet Dashboard
A1: Retirement Savings Planner
A3: FIRE Number $ | B3: Total Saved $ | C3: Progress % | D3: Years to FIRE
A4: =Settings!B4*25 | B4: =SUM(Accounts!C:C) | C4: =TEXT(SUM(Accounts!C:C)/(Settings!B4*25),"0%") | D4: =Settings!B6

Sheet Accounts
A1: Account | B1: Type | C1: Balance $ | D1: Annual Contribution | E1: Employer Match | F1: Return %
A2: 401k - Fidelity | C2: 85000 | D2: 7500 | E2: 3000 | F2: 7
A3: 401k - Fidelity | C3: 85000 | D3: 7500 | E3: 3000 | F3: 7
A4: 401k - Fidelity | C4: 85000 | D4: 7500 | E4: 3000 | F4: 7
A5: 401k - Fidelity | C5: 85000 | D5: 7500 | E5: 3000 | F5: 7
A6: 401k - Fidelity | C6: 85000 | D6: 7500 | E6: 3000 | F6: 7
A7: 401k - Fidelity | C7: 85000 | D7: 7500 | E7: 3000 | F7: 7

Sheet Projections
A1: Year | B1: Age | C1: Portfolio $ | D1: Annual Contribution | E1: Growth $ | F1: End Balance $
A2: 2024 | B2: 35 | C2: 125000 | D2: 15000 | E2: 8750 | F2: =C2+D2+E2
A3: 2024 | B3: 35 | C3: 125000 | D3: 15000 | E3: 8750 | F3: =C3+D3+E3
A4: 2024 | B4: 35 | C4: 125000 | D4: 15000 | E4: 8750 | F4: =C4+D4+E4
A5: 2024 | B5: 35 | C5: 125000 | D5: 15000 | E5: 8750 | F5: =C5+D5+E5
A6: 2024 | B6: 35 | C6: 125000 | D6: 15000 | E6: 8750 | F6: =C6+D6+E6
A7: 2024 | B7: 35 | C7: 125000 | D7: 15000 | E7: 8750 | F7: =C7+D7+E7
A8: 2024 | B8: 35 | C8: 125000 | D8: 15000 | E8: 8750 | F8: =C8+D8+E8
A9: 2024 | B9: 35 | C9: 125000 | D9: 15000 | E9: 8750 | F9: =C9+D9+E9
A10: 2024 | B10: 35 | C10: 125000 | D10: 15000 | E10: 8750 | F10: =C10+D10+E10
A11: 2024 | B11: 35 | C11: 125000 | D11: 15000 | E11: 8750 | F11: =C11+D11+E11
A12: 2024 | B12: 35 | C12: 125000 | D12: 15000 | E12: 8750 | F12: =C12+D12+E12
A13: 2024 | B13: 35 | C13: 125000 | D13: 15000 | E13: 8750 | F13: =C13+D13+E13
... A31: 2024 | B31: 35 | C31: 125000 | D31: 15000 | E31: 8750 | F31: =C31+D31+E31

Sheet Budget in Retirement
A1: Expense | B1: Monthly $ | C1: Annual $ | D1: Notes
A2: Housing | B2: 2000 | C2: =C2*12 | D2: Paid off mortgage by then
A3: Housing | B3: 2000 | C3: =C3*12 | D3: Paid off mortgage by then
A4: Housing | B4: 2000 | C4: =C4*12 | D4: Paid off mortgage by then
A5: Housing | B5: 2000 | C5: =C5*12 | D5: Paid off mortgage by then
A6: Housing | B6: 2000 | C6: =C6*12 | D6: Paid off mortgage by then
A7: Housing | B7: 2000 | C7: =C7*12 | D7: Paid off mortgage by then
A8: Housing | B8: 2000 | C8: =C8*12 | D8: Paid off mortgage by then
A9: Housing | B9: 2000 | C9: =C9*12 | D9: Paid off mortgage by then
A10: Housing | B10: 2000 | C10: =C10*12 | D10: Paid off mortgage by then
A11: Housing | B11: 2000 | C11: =C11*12 | D11: Paid off mortgage by then

Sheet FIRE Summary
A1: Reports — Auto-Generated
A3: Retirement Summary
A4: FIRE Number (25x) | B4: =Settings!B4*25
A5: Total Saved | B5: =SUM(Accounts!C:C)
A6: Annual Contribution | B6: =SUM(Accounts!D:D)
