Workbook

Sheet Dashboard
A1: Small Business Finance Tracker
A3: Total Revenue | B3: Total Expenses | C3: Net Profit | D3: Profit Margin
A4: =SUM(Revenue!C:C) | B4: =SUM(Expenses!D:D) | C4: =B4-C4 | D4: =TEXT(D4/B4,"0%")

Sheet Revenue
A1: Date | B1: Source | C1: Amount $ | D1: Category | E1: Notes
A2: 2024-01-05 | B2: Product Sales | C2: 2500 | E2: Jan batch sale
A3: 2024-01-05 | B3: Product Sales | C3: 2500 | E3: Jan batch sale
A4: 2024-01-05 | B4: Product Sales | C4: 2500 | E4: Jan batch sale
A5: 2024-01-05 | B5: Product Sales | C5: 2500 | E5: Jan batch sale
A6: 2024-01-05 | B6: Product Sales | C6: 2500 | E6: Jan batch sale
A7: 2024-01-05 | B7: Product Sales | C7: 2500 | E7: Jan batch sale
A8: 2024-01-05 | B8: Product Sales | C8: 2500 | E8: Jan batch sale
A9: 2024-01-05 | B9: Product Sales | C9: 2500 | E9: Jan batch sale
A10: 2024-01-05 | B10: Product Sales | C10: 2500 | E10: Jan batch sale
A11: 2024-01-05 | B11: Product Sales | C11: 2500 | E11: Jan batch sale
A12: 2024-01-05 | B12: Product Sales | C12: 2500 | E12: Jan batch sale
A13: 2024-01-05 | B13: Product Sales | C13: 2500 | E13: Jan batch sale
... A16: 2024-01-05 | B16: Product Sales | C16: 2500 | E16: Jan batch sale

Sheet Expenses
A1: Date | B1: Description | C1: Category | D1: Amount $ | E1: Deductible
A2: 2024-01-08 | B2: Office Supplies | D2: 320
A3: 2024-01-08 | B3: Office Supplies | D3: 320
A4: 2024-01-08 | B4: Office Supplies | D4: 320
A5: 2024-01-08 | B5: Office Supplies | D5: 320
A6: 2024-01-08 | B6: Office Supplies | D6: 320
A7: 2024-01-08 | B7: Office Supplies | D7: 320
A8: 2024-01-08 | B8: Office Supplies | D8: 320
A9: 2024-01-08 | B9: Office Supplies | D9: 320
A10: 2024-01-08 | B10: Office Supplies | D10: 320
A11: 2024-01-08 | B11: Office Supplies | D11: 320
A12: 2024-01-08 | B12: Office Supplies | D12: 320
A13: 2024-01-08 | B13: Office Supplies | D13: 320
... A16: 2024-01-08 | B16: Office Supplies | D16: 320

Sheet Monthly P&L
A1: Month | B1: Revenue $ | C1: Expenses $ | D1: Profit $ | E1: Margin %
A2: January 2024 | B2: 8500 | C2: 4200 | D2: =C2-D2 | E2: =TEXT(E2/C2,"0%")
A3: January 2024 | B3: 8500 | C3: 4200 | D3: =C3-D3 | E3: =TEXT(E3/C3,"0%")
A4: January 2024 | B4: 8500 | C4: 4200 | D4: =C4-D4 | E4: =TEXT(E4/C4,"0%")
A5: January 2024 | B5: 8500 | C5: 4200 | D5: =C5-D5 | E5: =TEXT(E5/C5,"0%")
A6: January 2024 | B6: 8500 | C6: 4200 | D6: =C6-D6 | E6: =TEXT(E6/C6,"0%")
A7: January 2024 | B7: 8500 | C7: 4200 | D7: =C7-D7 | E7: =TEXT(E7/C7,"0%")
A8: January 2024 | B8: 8500 | C8: 4200 | D8: =C8-D8 | E8: =TEXT(E8/C8,"0%")
A9: January 2024 | B9: 8500 | C9: 4200 | D9: =C9-D9 | E9: =TEXT(E9/C9,"0%")
A10: January 2024 | B10: 8500 | C10: 4200 | D10: =C10-D10 | E10: =TEXT(E10/C10,"0%")
A11: January 2024 | B11: 8500 | C11: 4200 | D11: =C11-D11 | E11: =TEXT(E11/C11,"0%")
A12: January 2024 | B12: 8500 | C12: 4200 | D12: =C12-D12 | E12: =TEXT(E12/C12,"0%")
A13: January 2024 | B13: 8500 | C13: 4200 | D13: =C13-D13 | E13: =TEXT(E13/C13,"0%")

Sheet Annual Report
A1: Reports — Auto-Generated
A3: Annual P&L
A4: Total Revenue | B4: =SUM(Revenue!C:C)
A5: Total Expenses | B5: =SUM(Expenses!D:D)
A6: Net Profit | B6: =SUM(Revenue!C:C)-SUM(Expenses!D:D)
