Workbook

Sheet START HERE
B2: ⏰ TIME TRACKING & TIMESHEET
B4: Billable Hours, Projects & Productivity Google Sheets
B6: STEP 1 — Fill in “Timesheet”
B7: Daily time log: project, task, hours, and billing status.
B9: STEP 2 — Fill in “Weekly Summary”
B10: Week-by-week time totals and billable breakdown.
B12: STEP 3 — Fill in “Project Summary”
B13: Hours and revenue per project.
B15: Then open the Dashboard — everything calculates automatically.
B17: TIP: Delete the sample rows once you've seen how it works.
B19: TIP: On Google Sheets? File → Make a copy first, then edit your copy.
B21: TIP: Columns with dropdowns keep your data clean — use them.
B23: Need help? Message NasriTools on Etsy — I reply fast. 🧡

Sheet Timesheet
A1: Date | B1: Project | C1: Task | D1: Hours | E1: Type | F1: Rate $/hr | G1: Client
A2: 46174 | B2: Kickoff meeting | C2: Kickoff meeting | D2: 3.5 | E2: Billable | F2: 85 | G2: Alex Martin
A3: 46180 | B3: Send proposal | C3: Send proposal | D3: 2.45 | E3: Non-Billable | F3: 59.5 | G3: Sara Lopez
A4: 46186 | B4: Review feedback | C4: Review feedback | D4: 4.55 | E4: Admin | F4: 110.5 | G4: Omar Haddad
A5: 46189 | B5: Update website copy | C5: Update website copy | D5: 2.98 | E5: Business Dev | F5: 72.25 | G5: Emma Fischer
A6: 46195 | B6: Prepare invoice | C6: Prepare invoice | D6: 4.02 | E6: Learning | F6: 97.75 | G6: Liam Carter
A7: 46201 | B7: Client call | C7: Client call | D7: 2.1 | E7: Billable | F7: 51 | G7: Nadia Rahali
A8: 46176 | B8: Design first draft | C8: Design first draft | D8: 5.08 | E8: Non-Billable | F8: 123.25 | G8: Tom Becker
A9: 46182 | B9: Fix reported bug | C9: Fix reported bug | D9: 3.32 | E9: Admin | F9: 80.75 | G9: Julia Romero
A10: 46188 | B10: Weekly report | C10: Weekly report | D10: 4.38 | E10: Business Dev | F10: 106.25 | G10: Karim Ziani
A11: 46191 | B11: Plan next sprint | C11: Plan next sprint | D11: 2.8 | E11: Learning | F11: 68 | G11: Anna Kowalska
A12: 46197 | B12: Publish blog post | C12: Publish blog post | D12: 3.85 | E12: Billable | F12: 93.5 | G12: David Chen
A13: 46175 | B13: Team sync | C13: Team sync | D13: 2.62 | E13: Non-Billable | F13: 63.75 | G13: Lea Moreau

Sheet Dashboard
B2: 📊 TIME TRACKING & TIMESHEET — DASHBOARD
B4: WEEKLY HOURS | D4: BILLABLE HOURS | F4: UTILIZATION % | H4: WEEKLY REVENUE $
B5: =SUM(Timesheet!D:D) | D5: =SUMIF(Timesheet!E:E,"Billable",Timesheet!D:D) | F5: =TEXT(SUMIF(Timesheet!E:E,"Billable",Timesheet!D:D)/SUM(Timesheet!D:D),"0%") | H5: =SUMPRODUCT((Timesheet!E:E="Billable")*Timesheet!D:D*Timesheet!F:F)
B8: WHAT'S INSIDE
B9: 📋 Timesheet — Daily time log: project, task, hours, and billing status.
B10: 📅 Weekly Summary — Week-by-week time totals and billable breakdown.
B11: 📊 Project Summary — Hours and revenue per project.
B12: 📊 Annual Report — Annual hours worked and revenue for tax reporting.
B14: Numbers update automatically as you fill the other tabs. Start with sample data deleted.

Sheet Weekly Summary
A1: Week | B1: Total Hours | C1: Billable Hrs | D1: Utilization % | E1: Revenue $
A2: Jan 15-19, 2024 | B2: 40 | C2: 32 | D2: =TEXT(C2/B2,"0%") | E2: 2720
A3: Jan 15-19, 2025 | B3: 28 | C3: 22.4 | D3: =TEXT(C3/B3,"0%") | E3: 1904
A4: Jan 15-19, 2026 | B4: 52 | C4: 41.6 | D4: =TEXT(C4/B4,"0%") | E4: 3536
A5: Jan 15-19, 2027 | B5: 34 | C5: 27.2 | D5: =TEXT(C5/B5,"0%") | E5: 2312
A6: Jan 15-19, 2028 | B6: 46 | C6: 36.8 | D6: =TEXT(C6/B6,"0%") | E6: 3128
A7: Jan 15-19, 2029 | B7: 24 | C7: 19.2 | D7: =TEXT(C7/B7,"0%") | E7: 1632
A8: Jan 15-19, 2030 | B8: 58 | C8: 46.4 | D8: =TEXT(C8/B8,"0%") | E8: 3944
A9: Jan 15-19, 2031 | B9: 38 | C9: 30.4 | D9: =TEXT(C9/B9,"0%") | E9: 2584
A10: Jan 15-19, 2032 | B10: 50 | C10: 40 | D10: =TEXT(C10/B10,"0%") | E10: 3400
A11: Jan 15-19, 2033 | B11: 32 | C11: 25.6 | D11: =TEXT(C11/B11,"0%") | E11: 2176
A12: Jan 15-19, 2034 | B12: 44 | C12: 35.2 | D12: =TEXT(C12/B12,"0%") | E12: 2992
A13: Jan 15-19, 2035 | B13: 30 | C13: 24 | D13: =TEXT(C13/B13,"0%") | E13: 2040

Sheet Project Summary
A1: Project | B1: Client | C1: Hours Logged | D1: Revenue $ | E1: Budget $ | F1: Remaining $
A2: Kickoff meeting | B2: Alex Martin | C2: 24 | D2: 2040 | E2: 3000 | F2: =E2-D2
A3: Send proposal | B3: Sara Lopez | C3: 16.8 | D3: 1428 | E3: 2100 | F3: =E3-D3
A4: Review feedback | B4: Omar Haddad | C4: 31.2 | D4: 2652 | E4: 3900 | F4: =E4-D4
A5: Update website copy | B5: Emma Fischer | C5: 20.4 | D5: 1734 | E5: 2550 | F5: =E5-D5
A6: Prepare invoice | B6: Liam Carter | C6: 27.6 | D6: 2346 | E6: 3450 | F6: =E6-D6
A7: Client call | B7: Nadia Rahali | C7: 14.4 | D7: 1224 | E7: 1800 | F7: =E7-D7
A8: Design first draft | B8: Tom Becker | C8: 34.8 | D8: 2958 | E8: 4350 | F8: =E8-D8
A9: Fix reported bug | B9: Julia Romero | C9: 22.8 | D9: 1938 | E9: 2850 | F9: =E9-D9
A10: Weekly report | B10: Karim Ziani | C10: 30 | D10: 2550 | E10: 3750 | F10: =E10-D10
A11: Plan next sprint | B11: Anna Kowalska | C11: 19.2 | D11: 1632 | E11: 2400 | F11: =E11-D11
A12: Publish blog post | B12: David Chen | C12: 26.4 | D12: 2244 | E12: 3300 | F12: =E12-D12
A13: Team sync | B13: Lea Moreau | C13: 18 | D13: 1530 | E13: 2250 | F13: =E13-D13

Sheet Annual Report
B2: 📈 ANNUAL REPORT
B4: Annual Time Summary
B5: Total Hours | C5: =SUM(Timesheet!D:D)
B6: Billable Hours | C6: =SUMIF(Timesheet!E:E,"Billable",Timesheet!D:D)
B7: Total Revenue | C7: =SUMPRODUCT((Timesheet!E:E="Billable")*Timesheet!D:D*Timesheet!F:F)
