Workbook

Sheet Dashboard
A1: Personal Budget Tracker
A3: Income | B3: Expenses | C3: Savings | D3: Rate
A4: =SUM(Income!B:B) | B4: =SUM(Expenses!D:D) | C4: =B4-C4 | D4: =TEXT(D4/B4,"0%")

Sheet Income
A1: Date | B1: Amount | C1: Source | D1: Category | E1: Notes
A2: 2024-01-01 | B2: 3000 | C2: Salary | E2: Monthly salary
A3: 2024-01-01 | B3: 3000 | C3: Salary | E3: Monthly salary
A4: 2024-01-01 | B4: 3000 | C4: Salary | E4: Monthly salary
A5: 2024-01-01 | B5: 3000 | C5: Salary | E5: Monthly salary
A6: 2024-01-01 | B6: 3000 | C6: Salary | E6: Monthly salary
A7: 2024-01-01 | B7: 3000 | C7: Salary | E7: Monthly salary
A8: 2024-01-01 | B8: 3000 | C8: Salary | E8: Monthly salary
A9: 2024-01-01 | B9: 3000 | C9: Salary | E9: Monthly salary

Sheet Expenses
A1: Date | B1: Item | C1: Category | D1: Amount | E1: Budget | F1: Notes
A2: 2024-01-05 | B2: Rent | D2: 800 | E2: 850 | F2: Monthly rent
A3: 2024-01-05 | B3: Rent | D3: 800 | E3: 850 | F3: Monthly rent
A4: 2024-01-05 | B4: Rent | D4: 800 | E4: 850 | F4: Monthly rent
A5: 2024-01-05 | B5: Rent | D5: 800 | E5: 850 | F5: Monthly rent
A6: 2024-01-05 | B6: Rent | D6: 800 | E6: 850 | F6: Monthly rent
A7: 2024-01-05 | B7: Rent | D7: 800 | E7: 850 | F7: Monthly rent
A8: 2024-01-05 | B8: Rent | D8: 800 | E8: 850 | F8: Monthly rent
A9: 2024-01-05 | B9: Rent | D9: 800 | E9: 850 | F9: Monthly rent
A10: 2024-01-05 | B10: Rent | D10: 800 | E10: 850 | F10: Monthly rent
A11: 2024-01-05 | B11: Rent | D11: 800 | E11: 850 | F11: Monthly rent
A12: 2024-01-05 | B12: Rent | D12: 800 | E12: 850 | F12: Monthly rent
A13: 2024-01-05 | B13: Rent | D13: 800 | E13: 850 | F13: Monthly rent

Sheet Savings Goals
A1: Goal | B1: Target | C1: Saved | D1: Progress | E1: Deadline
A2: Emergency Fund | B2: 5000 | C2: 1200 | D2: =TEXT(D2/C2,"0%") | E2: 2024-12-31
A3: Emergency Fund | B3: 5000 | C3: 1200 | D3: =TEXT(D3/C3,"0%") | E3: 2024-12-31
A4: Emergency Fund | B4: 5000 | C4: 1200 | D4: =TEXT(D4/C4,"0%") | E4: 2024-12-31
A5: Emergency Fund | B5: 5000 | C5: 1200 | D5: =TEXT(D5/C5,"0%") | E5: 2024-12-31
A6: Emergency Fund | B6: 5000 | C6: 1200 | D6: =TEXT(D6/C6,"0%") | E6: 2024-12-31

Sheet Monthly View
A1: Month | B1: Income | C1: Expenses | D1: Savings | E1: Rate
A2: January 2024 | B2: 3000 | C2: 2100 | D2: =C2-D2 | E2: =TEXT(E2/C2,"0%")
A3: January 2024 | B3: 3000 | C3: 2100 | D3: =C3-D3 | E3: =TEXT(E3/C3,"0%")
A4: January 2024 | B4: 3000 | C4: 2100 | D4: =C4-D4 | E4: =TEXT(E4/C4,"0%")
A5: January 2024 | B5: 3000 | C5: 2100 | D5: =C5-D5 | E5: =TEXT(E5/C5,"0%")
A6: January 2024 | B6: 3000 | C6: 2100 | D6: =C6-D6 | E6: =TEXT(E6/C6,"0%")
A7: January 2024 | B7: 3000 | C7: 2100 | D7: =C7-D7 | E7: =TEXT(E7/C7,"0%")
A8: January 2024 | B8: 3000 | C8: 2100 | D8: =C8-D8 | E8: =TEXT(E8/C8,"0%")
A9: January 2024 | B9: 3000 | C9: 2100 | D9: =C9-D9 | E9: =TEXT(E9/C9,"0%")
A10: January 2024 | B10: 3000 | C10: 2100 | D10: =C10-D10 | E10: =TEXT(E10/C10,"0%")
A11: January 2024 | B11: 3000 | C11: 2100 | D11: =C11-D11 | E11: =TEXT(E11/C11,"0%")
A12: January 2024 | B12: 3000 | C12: 2100 | D12: =C12-D12 | E12: =TEXT(E12/C12,"0%")
A13: January 2024 | B13: 3000 | C13: 2100 | D13: =C13-D13 | E13: =TEXT(E13/C13,"0%")

Sheet Reports
A1: Reports — Auto-Generated
A3: Annual Summary
A4: Total Income | B4: =SUM(Income!B:B)
A5: Total Expenses | B5: =SUM(Expenses!D:D)
A6: Total Savings | B6: =SUM(Income!B:B)-SUM(Expenses!D:D)
